{
  "type": "FeatureCollection",
  "features": [
    {
      "type": "Feature",
      "properties": { "name": "Building A", "type": "building" },
      "geometry": {
        "type": "Polygon",
        "coordinates": [
          [
            [21.0336, 52.1506],
            [21.034, 52.1506],
            [21.034, 52.1509],
            [21.0336, 52.1509],
            [21.0336, 52.1506]
          ]
        ]
      }
    },
    {
      "type": "Feature",
      "properties": { "name": "Park X", "type": "park" },
      "geometry": {
        "type": "Polygon",
        "coordinates": [
          [
            [21.0325, 52.15],
            [21.033, 52.15],
            [21.033, 52.1503],
            [21.0325, 52.1503],
            [21.0325, 52.15]
          ]
        ]
      }
    }
  ]
}
